{
  "generator-jhipster": {
    "promptValues": {
      "packageName": "in.vagabond.lms",
      "nativeLanguage": "en"
    },
    "jhipsterVersion": "4.2.0",
    "baseName": "lms",
    "packageName": "in.vagabond.lms",
    "packageFolder": "in/vagabond/lms",
    "serverPort": "8080",
    "authenticationType": "session",
    "hibernateCache": "no",
    "clusteredHttpSession": false,
    "websocket": false,
    "databaseType": "sql",
    "devDatabaseType": "h2Memory",
    "prodDatabaseType": "postgresql",
    "searchEngine": false,
    "messageBroker": false,
    "serviceDiscoveryType": false,
    "buildTool": "maven",
    "enableSocialSignIn": false,
    "rememberMeKey": "cbd710324218883a72ef1fc2e0dbbb3536f60eb4",
    "clientFramework": "angular2",
    "useSass": false,
    "clientPackageManager": "npm",
    "applicationType": "monolith",
    "testFrameworks": [],
    "jhiPrefix": "jhi",
    "enableTranslation": true,
    "nativeLanguage": "en",
    "languages": [
      "en"
    ]
  }
}